{"backend_access_log":{"name":"backend_access_log","engine":"InnoDB","collation":"utf8mb4_unicode_ci","comment":"","primaryKey":"id","columns":{"id":{"name":"id","type":"int(10) unsigned","nullable":false,"default":null,"comment":"","isPrimaryKey":true,"isForeignKey":false,"relation":[],"autoIncrement":true},"user_id":{"name":"user_id","type":"int(10) unsigned","nullable":false,"default":null,"comment":"","isPrimaryKey":false,"isForeignKey":false,"relation":[],"autoIncrement":false},"ip_address":{"name":"ip_address","type":"varchar(191)","nullable":true,"default":null,"comment":"","isPrimaryKey":false,"isForeignKey":false,"relation":[],"autoIncrement":false},"created_at":{"name":"created_at","type":"timestamp","nullable":true,"default":null,"comment":"","isPrimaryKey":false,"isForeignKey":false,"relation":[],"autoIncrement":false},"updated_at":{"name":"updated_at","type":"timestamp","nullable":true,"default":null,"comment":"","isPrimaryKey":false,"isForeignKey":false,"relation":[],"autoIncrement":false}},"indexes":{"PRIMARY":{"name":"PRIMARY","columns":{"1":{"name":"id","sub_part":null}},"unique":true,"type":"BTREE","comment":"","null":null},"":{"name":null,"columns":{"":{"name":null,"sub_part":null}},"unique":true,"type":null,"comment":null,"null":"NULL"}},"foreignKeys":[]},"backend_user_groups":{"name":"backend_user_groups","engine":"InnoDB","collation":"utf8mb4_unicode_ci","comment":"","primaryKey":"id","columns":{"id":{"name":"id","type":"int(10) unsigned","nullable":false,"default":null,"comment":"","isPrimaryKey":true,"isForeignKey":false,"relation":[],"autoIncrement":true},"name":{"name":"name","type":"varchar(191)","nullable":false,"default":null,"comment":"","isPrimaryKey":false,"isForeignKey":false,"relation":[],"autoIncrement":false},"created_at":{"name":"created_at","type":"timestamp","nullable":true,"default":null,"comment":"","isPrimaryKey":false,"isForeignKey":false,"relation":[],"autoIncrement":false},"updated_at":{"name":"updated_at","type":"timestamp","nullable":true,"default":null,"comment":"","isPrimaryKey":false,"isForeignKey":false,"relation":[],"autoIncrement":false},"code":{"name":"code","type":"varchar(191)","nullable":true,"default":null,"comment":"","isPrimaryKey":false,"isForeignKey":false,"relation":[],"autoIncrement":false},"description":{"name":"description","type":"text","nullable":true,"default":null,"comment":"","isPrimaryKey":false,"isForeignKey":false,"relation":[],"autoIncrement":false},"is_new_user_default":{"name":"is_new_user_default","type":"tinyint(1)","nullable":false,"default":"0","comment":"","isPrimaryKey":false,"isForeignKey":false,"relation":[],"autoIncrement":false}},"indexes":{"PRIMARY":{"name":"PRIMARY","columns":{"1":{"name":"id","sub_part":null}},"unique":true,"type":"BTREE","comment":"","null":null},"name_unique":{"name":"name_unique","columns":{"1":{"name":"name","sub_part":null}},"unique":true,"type":"BTREE","comment":"","null":null},"code_index":{"name":"code_index","columns":{"1":{"name":"code","sub_part":null}},"unique":false,"type":"BTREE","comment":"","null":null},"":{"name":null,"columns":{"":{"name":null,"sub_part":null}},"unique":true,"type":null,"comment":null,"null":"NULL"}},"foreignKeys":[]},"backend_user_preferences":{"name":"backend_user_preferences","engine":"InnoDB","collation":"utf8mb4_unicode_ci","comment":"","primaryKey":"id","columns":{"id":{"name":"id","type":"int(10) unsigned","nullable":false,"default":null,"comment":"","isPrimaryKey":true,"isForeignKey":false,"relation":[],"autoIncrement":true},"user_id":{"name":"user_id","type":"int(10) unsigned","nullable":false,"default":null,"comment":"","isPrimaryKey":false,"isForeignKey":false,"relation":[],"autoIncrement":false},"namespace":{"name":"namespace","type":"varchar(100)","nullable":false,"default":null,"comment":"","isPrimaryKey":false,"isForeignKey":false,"relation":[],"autoIncrement":false},"group":{"name":"group","type":"varchar(50)","nullable":false,"default":null,"comment":"","isPrimaryKey":false,"isForeignKey":false,"relation":[],"autoIncrement":false},"item":{"name":"item","type":"varchar(150)","nullable":false,"default":null,"comment":"","isPrimaryKey":false,"isForeignKey":false,"relation":[],"autoIncrement":false},"value":{"name":"value","type":"text","nullable":true,"default":null,"comment":"","isPrimaryKey":false,"isForeignKey":false,"relation":[],"autoIncrement":false}},"indexes":{"PRIMARY":{"name":"PRIMARY","columns":{"1":{"name":"id","sub_part":null}},"unique":true,"type":"BTREE","comment":"","null":null},"user_item_index":{"name":"user_item_index","columns":{"1":{"name":"user_id","sub_part":null},"2":{"name":"namespace","sub_part":null},"3":{"name":"group","sub_part":null},"4":{"name":"item","sub_part":null}},"unique":false,"type":"BTREE","comment":"","null":null},"":{"name":null,"columns":{"":{"name":null,"sub_part":null}},"unique":true,"type":null,"comment":null,"null":"NULL"}},"foreignKeys":[]},"backend_user_roles":{"name":"backend_user_roles","engine":"InnoDB","collation":"utf8mb4_unicode_ci","comment":"","primaryKey":"id","columns":{"id":{"name":"id","type":"int(10) unsigned","nullable":false,"default":null,"comment":"","isPrimaryKey":true,"isForeignKey":false,"relation":[],"autoIncrement":true},"name":{"name":"name","type":"varchar(191)","nullable":false,"default":null,"comment":"","isPrimaryKey":false,"isForeignKey":false,"relation":[],"autoIncrement":false},"code":{"name":"code","type":"varchar(191)","nullable":true,"default":null,"comment":"","isPrimaryKey":false,"isForeignKey":false,"relation":[],"autoIncrement":false},"description":{"name":"description","type":"text","nullable":true,"default":null,"comment":"","isPrimaryKey":false,"isForeignKey":false,"relation":[],"autoIncrement":false},"permissions":{"name":"permissions","type":"text","nullable":true,"default":null,"comment":"","isPrimaryKey":false,"isForeignKey":false,"relation":[],"autoIncrement":false},"is_system":{"name":"is_system","type":"tinyint(1)","nullable":false,"default":"0","comment":"","isPrimaryKey":false,"isForeignKey":false,"relation":[],"autoIncrement":false},"created_at":{"name":"created_at","type":"timestamp","nullable":true,"default":null,"comment":"","isPrimaryKey":false,"isForeignKey":false,"relation":[],"autoIncrement":false},"updated_at":{"name":"updated_at","type":"timestamp","nullable":true,"default":null,"comment":"","isPrimaryKey":false,"isForeignKey":false,"relation":[],"autoIncrement":false}},"indexes":{"PRIMARY":{"name":"PRIMARY","columns":{"1":{"name":"id","sub_part":null}},"unique":true,"type":"BTREE","comment":"","null":null},"role_unique":{"name":"role_unique","columns":{"1":{"name":"name","sub_part":null}},"unique":true,"type":"BTREE","comment":"","null":null},"role_code_index":{"name":"role_code_index","columns":{"1":{"name":"code","sub_part":null}},"unique":false,"type":"BTREE","comment":"","null":null},"":{"name":null,"columns":{"":{"name":null,"sub_part":null}},"unique":true,"type":null,"comment":null,"null":"NULL"}},"foreignKeys":[]},"backend_user_throttle":{"name":"backend_user_throttle","engine":"InnoDB","collation":"utf8mb4_unicode_ci","comment":"","primaryKey":"id","columns":{"id":{"name":"id","type":"int(10) unsigned","nullable":false,"default":null,"comment":"","isPrimaryKey":true,"isForeignKey":false,"relation":[],"autoIncrement":true},"user_id":{"name":"user_id","type":"int(10) unsigned","nullable":true,"default":null,"comment":"","isPrimaryKey":false,"isForeignKey":false,"relation":[],"autoIncrement":false},"ip_address":{"name":"ip_address","type":"varchar(191)","nullable":true,"default":null,"comment":"","isPrimaryKey":false,"isForeignKey":false,"relation":[],"autoIncrement":false},"attempts":{"name":"attempts","type":"int(11)","nullable":false,"default":"0","comment":"","isPrimaryKey":false,"isForeignKey":false,"relation":[],"autoIncrement":false},"last_attempt_at":{"name":"last_attempt_at","type":"timestamp","nullable":true,"default":null,"comment":"","isPrimaryKey":false,"isForeignKey":false,"relation":[],"autoIncrement":false},"is_suspended":{"name":"is_suspended","type":"tinyint(1)","nullable":false,"default":"0","comment":"","isPrimaryKey":false,"isForeignKey":false,"relation":[],"autoIncrement":false},"suspended_at":{"name":"suspended_at","type":"timestamp","nullable":true,"default":null,"comment":"","isPrimaryKey":false,"isForeignKey":false,"relation":[],"autoIncrement":false},"is_banned":{"name":"is_banned","type":"tinyint(1)","nullable":false,"default":"0","comment":"","isPrimaryKey":false,"isForeignKey":false,"relation":[],"autoIncrement":false},"banned_at":{"name":"banned_at","type":"timestamp","nullable":true,"default":null,"comment":"","isPrimaryKey":false,"isForeignKey":false,"relation":[],"autoIncrement":false}},"indexes":{"PRIMARY":{"name":"PRIMARY","columns":{"1":{"name":"id","sub_part":null}},"unique":true,"type":"BTREE","comment":"","null":null},"backend_user_throttle_user_id_index":{"name":"backend_user_throttle_user_id_index","columns":{"1":{"name":"user_id","sub_part":null}},"unique":false,"type":"BTREE","comment":"","null":null},"backend_user_throttle_ip_address_index":{"name":"backend_user_throttle_ip_address_index","columns":{"1":{"name":"ip_address","sub_part":null}},"unique":false,"type":"BTREE","comment":"","null":null},"":{"name":null,"columns":{"":{"name":null,"sub_part":null}},"unique":true,"type":null,"comment":null,"null":"NULL"}},"foreignKeys":[]},"backend_users":{"name":"backend_users","engine":"InnoDB","collation":"utf8mb4_unicode_ci","comment":"","primaryKey":"id","columns":{"id":{"name":"id","type":"int(10) unsigned","nullable":false,"default":null,"comment":"","isPrimaryKey":true,"isForeignKey":false,"relation":[],"autoIncrement":true},"first_name":{"name":"first_name","type":"varchar(191)","nullable":true,"default":null,"comment":"","isPrimaryKey":false,"isForeignKey":false,"relation":[],"autoIncrement":false},"last_name":{"name":"last_name","type":"varchar(191)","nullable":true,"default":null,"comment":"","isPrimaryKey":false,"isForeignKey":false,"relation":[],"autoIncrement":false},"login":{"name":"login","type":"varchar(191)","nullable":false,"default":null,"comment":"","isPrimaryKey":false,"isForeignKey":false,"relation":[],"autoIncrement":false},"email":{"name":"email","type":"varchar(191)","nullable":false,"default":null,"comment":"","isPrimaryKey":false,"isForeignKey":false,"relation":[],"autoIncrement":false},"password":{"name":"password","type":"varchar(191)","nullable":false,"default":null,"comment":"","isPrimaryKey":false,"isForeignKey":false,"relation":[],"autoIncrement":false},"activation_code":{"name":"activation_code","type":"varchar(191)","nullable":true,"default":null,"comment":"","isPrimaryKey":false,"isForeignKey":false,"relation":[],"autoIncrement":false},"persist_code":{"name":"persist_code","type":"varchar(191)","nullable":true,"default":null,"comment":"","isPrimaryKey":false,"isForeignKey":false,"relation":[],"autoIncrement":false},"reset_password_code":{"name":"reset_password_code","type":"varchar(191)","nullable":true,"default":null,"comment":"","isPrimaryKey":false,"isForeignKey":false,"relation":[],"autoIncrement":false},"permissions":{"name":"permissions","type":"text","nullable":true,"default":null,"comment":"","isPrimaryKey":false,"isForeignKey":false,"relation":[],"autoIncrement":false},"is_activated":{"name":"is_activated","type":"tinyint(1)","nullable":false,"default":"0","comment":"","isPrimaryKey":false,"isForeignKey":false,"relation":[],"autoIncrement":false},"role_id":{"name":"role_id","type":"int(10) unsigned","nullable":true,"default":null,"comment":"","isPrimaryKey":false,"isForeignKey":false,"relation":[],"autoIncrement":false},"activated_at":{"name":"activated_at","type":"timestamp","nullable":true,"default":null,"comment":"","isPrimaryKey":false,"isForeignKey":false,"relation":[],"autoIncrement":false},"last_login":{"name":"last_login","type":"timestamp","nullable":true,"default":null,"comment":"","isPrimaryKey":false,"isForeignKey":false,"relation":[],"autoIncrement":false},"created_at":{"name":"created_at","type":"timestamp","nullable":true,"default":null,"comment":"","isPrimaryKey":false,"isForeignKey":false,"relation":[],"autoIncrement":false},"updated_at":{"name":"updated_at","type":"timestamp","nullable":true,"default":null,"comment":"","isPrimaryKey":false,"isForeignKey":false,"relation":[],"autoIncrement":false},"is_superuser":{"name":"is_superuser","type":"tinyint(1)","nullable":false,"default":"0","comment":"","isPrimaryKey":false,"isForeignKey":false,"relation":[],"autoIncrement":false}},"indexes":{"PRIMARY":{"name":"PRIMARY","columns":{"1":{"name":"id","sub_part":null}},"unique":true,"type":"BTREE","comment":"","null":null},"login_unique":{"name":"login_unique","columns":{"1":{"name":"login","sub_part":null}},"unique":true,"type":"BTREE","comment":"","null":null},"email_unique":{"name":"email_unique","columns":{"1":{"name":"email","sub_part":null}},"unique":true,"type":"BTREE","comment":"","null":null},"act_code_index":{"name":"act_code_index","columns":{"1":{"name":"activation_code","sub_part":null}},"unique":false,"type":"BTREE","comment":"","null":null},"reset_code_index":{"name":"reset_code_index","columns":{"1":{"name":"reset_password_code","sub_part":null}},"unique":false,"type":"BTREE","comment":"","null":null},"admin_role_index":{"name":"admin_role_index","columns":{"1":{"name":"role_id","sub_part":null}},"unique":false,"type":"BTREE","comment":"","null":null},"":{"name":null,"columns":{"":{"name":null,"sub_part":null}},"unique":true,"type":null,"comment":null,"null":"NULL"}},"foreignKeys":[]},"backend_users_groups":{"name":"backend_users_groups","engine":"InnoDB","collation":"utf8mb4_unicode_ci","comment":"","primaryKey":["user_id","user_group_id"],"columns":{"user_id":{"name":"user_id","type":"int(10) unsigned","nullable":false,"default":null,"comment":"","isPrimaryKey":true,"isForeignKey":false,"relation":[],"autoIncrement":false},"user_group_id":{"name":"user_group_id","type":"int(10) unsigned","nullable":false,"default":null,"comment":"","isPrimaryKey":true,"isForeignKey":false,"relation":[],"autoIncrement":false}},"indexes":{"PRIMARY":{"name":"PRIMARY","columns":{"1":{"name":"user_id","sub_part":null},"2":{"name":"user_group_id","sub_part":null}},"unique":true,"type":"BTREE","comment":"","null":null},"":{"name":null,"columns":{"":{"name":null,"sub_part":null}},"unique":true,"type":null,"comment":null,"null":"NULL"}},"foreignKeys":[]},"cache":{"name":"cache","engine":"InnoDB","collation":"utf8mb4_unicode_ci","comment":"","primaryKey":"key","columns":{"key":{"name":"key","type":"varchar(191)","nullable":false,"default":null,"comment":"","isPrimaryKey":true,"isForeignKey":false,"relation":[],"autoIncrement":false},"value":{"name":"value","type":"longtext","nullable":false,"default":null,"comment":"","isPrimaryKey":false,"isForeignKey":false,"relation":[],"autoIncrement":false},"expiration":{"name":"expiration","type":"int(11)","nullable":false,"default":null,"comment":"","isPrimaryKey":false,"isForeignKey":false,"relation":[],"autoIncrement":false}},"indexes":{"cache_key_unique":{"name":"cache_key_unique","columns":{"1":{"name":"key","sub_part":null}},"unique":true,"type":"BTREE","comment":"","null":null},"":{"name":null,"columns":{"":{"name":null,"sub_part":null}},"unique":true,"type":null,"comment":null,"null":"NULL"}},"foreignKeys":[]},"cms_theme_data":{"name":"cms_theme_data","engine":"InnoDB","collation":"utf8mb4_unicode_ci","comment":"","primaryKey":"id","columns":{"id":{"name":"id","type":"int(10) unsigned","nullable":false,"default":null,"comment":"","isPrimaryKey":true,"isForeignKey":false,"relation":[],"autoIncrement":true},"theme":{"name":"theme","type":"varchar(191)","nullable":true,"default":null,"comment":"","isPrimaryKey":false,"isForeignKey":false,"relation":[],"autoIncrement":false},"data":{"name":"data","type":"mediumtext","nullable":true,"default":null,"comment":"","isPrimaryKey":false,"isForeignKey":false,"relation":[],"autoIncrement":false},"created_at":{"name":"created_at","type":"timestamp","nullable":true,"default":null,"comment":"","isPrimaryKey":false,"isForeignKey":false,"relation":[],"autoIncrement":false},"updated_at":{"name":"updated_at","type":"timestamp","nullable":true,"default":null,"comment":"","isPrimaryKey":false,"isForeignKey":false,"relation":[],"autoIncrement":false}},"indexes":{"PRIMARY":{"name":"PRIMARY","columns":{"1":{"name":"id","sub_part":null}},"unique":true,"type":"BTREE","comment":"","null":null},"cms_theme_data_theme_index":{"name":"cms_theme_data_theme_index","columns":{"1":{"name":"theme","sub_part":null}},"unique":false,"type":"BTREE","comment":"","null":null},"":{"name":null,"columns":{"":{"name":null,"sub_part":null}},"unique":true,"type":null,"comment":null,"null":"NULL"}},"foreignKeys":[]},"cms_theme_logs":{"name":"cms_theme_logs","engine":"InnoDB","collation":"utf8mb4_unicode_ci","comment":"","primaryKey":"id","columns":{"id":{"name":"id","type":"int(10) unsigned","nullable":false,"default":null,"comment":"","isPrimaryKey":true,"isForeignKey":false,"relation":[],"autoIncrement":true},"type":{"name":"type","type":"varchar(20)","nullable":false,"default":null,"comment":"","isPrimaryKey":false,"isForeignKey":false,"relation":[],"autoIncrement":false},"theme":{"name":"theme","type":"varchar(191)","nullable":true,"default":null,"comment":"","isPrimaryKey":false,"isForeignKey":false,"relation":[],"autoIncrement":false},"template":{"name":"template","type":"varchar(191)","nullable":true,"default":null,"comment":"","isPrimaryKey":false,"isForeignKey":false,"relation":[],"autoIncrement":false},"old_template":{"name":"old_template","type":"varchar(191)","nullable":true,"default":null,"comment":"","isPrimaryKey":false,"isForeignKey":false,"relation":[],"autoIncrement":false},"content":{"name":"content","type":"longtext","nullable":true,"default":null,"comment":"","isPrimaryKey":false,"isForeignKey":false,"relation":[],"autoIncrement":false},"old_content":{"name":"old_content","type":"longtext","nullable":true,"default":null,"comment":"","isPrimaryKey":false,"isForeignKey":false,"relation":[],"autoIncrement":false},"user_id":{"name":"user_id","type":"int(11)","nullable":true,"default":null,"comment":"","isPrimaryKey":false,"isForeignKey":false,"relation":[],"autoIncrement":false},"created_at":{"name":"created_at","type":"timestamp","nullable":true,"default":null,"comment":"","isPrimaryKey":false,"isForeignKey":false,"relation":[],"autoIncrement":false},"updated_at":{"name":"updated_at","type":"timestamp","nullable":true,"default":null,"comment":"","isPrimaryKey":false,"isForeignKey":false,"relation":[],"autoIncrement":false}},"indexes":{"PRIMARY":{"name":"PRIMARY","columns":{"1":{"name":"id","sub_part":null}},"unique":true,"type":"BTREE","comment":"","null":null},"cms_theme_logs_type_index":{"name":"cms_theme_logs_type_index","columns":{"1":{"name":"type","sub_part":null}},"unique":false,"type":"BTREE","comment":"","null":null},"cms_theme_logs_theme_index":{"name":"cms_theme_logs_theme_index","columns":{"1":{"name":"theme","sub_part":null}},"unique":false,"type":"BTREE","comment":"","null":null},"cms_theme_logs_user_id_index":{"name":"cms_theme_logs_user_id_index","columns":{"1":{"name":"user_id","sub_part":null}},"unique":false,"type":"BTREE","comment":"","null":null},"":{"name":null,"columns":{"":{"name":null,"sub_part":null}},"unique":true,"type":null,"comment":null,"null":"NULL"}},"foreignKeys":[]},"deferred_bindings":{"name":"deferred_bindings","engine":"InnoDB","collation":"utf8mb4_unicode_ci","comment":"","primaryKey":"id","columns":{"id":{"name":"id","type":"int(10) unsigned","nullable":false,"default":null,"comment":"","isPrimaryKey":true,"isForeignKey":false,"relation":[],"autoIncrement":true},"master_type":{"name":"master_type","type":"varchar(191)","nullable":false,"default":null,"comment":"","isPrimaryKey":false,"isForeignKey":false,"relation":[],"autoIncrement":false},"master_field":{"name":"master_field","type":"varchar(191)","nullable":false,"default":null,"comment":"","isPrimaryKey":false,"isForeignKey":false,"relation":[],"autoIncrement":false},"slave_type":{"name":"slave_type","type":"varchar(191)","nullable":false,"default":null,"comment":"","isPrimaryKey":false,"isForeignKey":false,"relation":[],"autoIncrement":false},"slave_id":{"name":"slave_id","type":"varchar(191)","nullable":false,"default":null,"comment":"","isPrimaryKey":false,"isForeignKey":false,"relation":[],"autoIncrement":false},"session_key":{"name":"session_key","type":"varchar(191)","nullable":false,"default":null,"comment":"","isPrimaryKey":false,"isForeignKey":false,"relation":[],"autoIncrement":false},"is_bind":{"name":"is_bind","type":"tinyint(1)","nullable":false,"default":"1","comment":"","isPrimaryKey":false,"isForeignKey":false,"relation":[],"autoIncrement":false},"created_at":{"name":"created_at","type":"timestamp","nullable":true,"default":null,"comment":"","isPrimaryKey":false,"isForeignKey":false,"relation":[],"autoIncrement":false},"updated_at":{"name":"updated_at","type":"timestamp","nullable":true,"default":null,"comment":"","isPrimaryKey":false,"isForeignKey":false,"relation":[],"autoIncrement":false}},"indexes":{"PRIMARY":{"name":"PRIMARY","columns":{"1":{"name":"id","sub_part":null}},"unique":true,"type":"BTREE","comment":"","null":null},"deferred_bindings_master_type_index":{"name":"deferred_bindings_master_type_index","columns":{"1":{"name":"master_type","sub_part":null}},"unique":false,"type":"BTREE","comment":"","null":null},"deferred_bindings_master_field_index":{"name":"deferred_bindings_master_field_index","columns":{"1":{"name":"master_field","sub_part":null}},"unique":false,"type":"BTREE","comment":"","null":null},"deferred_bindings_slave_type_index":{"name":"deferred_bindings_slave_type_index","columns":{"1":{"name":"slave_type","sub_part":null}},"unique":false,"type":"BTREE","comment":"","null":null},"deferred_bindings_slave_id_index":{"name":"deferred_bindings_slave_id_index","columns":{"1":{"name":"slave_id","sub_part":null}},"unique":false,"type":"BTREE","comment":"","null":null},"deferred_bindings_session_key_index":{"name":"deferred_bindings_session_key_index","columns":{"1":{"name":"session_key","sub_part":null}},"unique":false,"type":"BTREE","comment":"","null":null},"":{"name":null,"columns":{"":{"name":null,"sub_part":null}},"unique":true,"type":null,"comment":null,"null":"NULL"}},"foreignKeys":[]},"failed_jobs":{"name":"failed_jobs","engine":"InnoDB","collation":"utf8mb4_unicode_ci","comment":"","primaryKey":"id","columns":{"id":{"name":"id","type":"int(10) unsigned","nullable":false,"default":null,"comment":"","isPrimaryKey":true,"isForeignKey":false,"relation":[],"autoIncrement":true},"connection":{"name":"connection","type":"text","nullable":false,"default":null,"comment":"","isPrimaryKey":false,"isForeignKey":false,"relation":[],"autoIncrement":false},"queue":{"name":"queue","type":"text","nullable":false,"default":null,"comment":"","isPrimaryKey":false,"isForeignKey":false,"relation":[],"autoIncrement":false},"payload":{"name":"payload","type":"text","nullable":false,"default":null,"comment":"","isPrimaryKey":false,"isForeignKey":false,"relation":[],"autoIncrement":false},"exception":{"name":"exception","type":"longtext","nullable":true,"default":null,"comment":"","isPrimaryKey":false,"isForeignKey":false,"relation":[],"autoIncrement":false},"failed_at":{"name":"failed_at","type":"timestamp","nullable":true,"default":null,"comment":"","isPrimaryKey":false,"isForeignKey":false,"relation":[],"autoIncrement":false}},"indexes":{"PRIMARY":{"name":"PRIMARY","columns":{"1":{"name":"id","sub_part":null}},"unique":true,"type":"BTREE","comment":"","null":null},"":{"name":null,"columns":{"":{"name":null,"sub_part":null}},"unique":true,"type":null,"comment":null,"null":"NULL"}},"foreignKeys":[]},"indikator_news_categories":{"name":"indikator_news_categories","engine":"InnoDB","collation":"utf8mb4_unicode_ci","comment":"","primaryKey":"id","columns":{"id":{"name":"id","type":"int(10) unsigned","nullable":false,"default":null,"comment":"","isPrimaryKey":true,"isForeignKey":false,"relation":[],"autoIncrement":true},"name":{"name":"name","type":"varchar(100)","nullable":false,"default":null,"comment":"","isPrimaryKey":false,"isForeignKey":false,"relation":[],"autoIncrement":false},"slug":{"name":"slug","type":"varchar(100)","nullable":false,"default":null,"comment":"","isPrimaryKey":false,"isForeignKey":false,"relation":[],"autoIncrement":false},"content":{"name":"content","type":"longtext","nullable":true,"default":null,"comment":"","isPrimaryKey":false,"isForeignKey":false,"relation":[],"autoIncrement":false},"image":{"name":"image","type":"varchar(200)","nullable":true,"default":null,"comment":"","isPrimaryKey":false,"isForeignKey":false,"relation":[],"autoIncrement":false},"hidden":{"name":"hidden","type":"varchar(1)","nullable":false,"default":"2","comment":"","isPrimaryKey":false,"isForeignKey":false,"relation":[],"autoIncrement":false},"status":{"name":"status","type":"varchar(1)","nullable":false,"default":"1","comment":"","isPrimaryKey":false,"isForeignKey":false,"relation":[],"autoIncrement":false},"sort_order":{"name":"sort_order","type":"varchar(3)","nullable":false,"default":"1","comment":"","isPrimaryKey":false,"isForeignKey":false,"relation":[],"autoIncrement":false},"created_at":{"name":"created_at","type":"timestamp","nullable":true,"default":null,"comment":"","isPrimaryKey":false,"isForeignKey":false,"relation":[],"autoIncrement":false},"updated_at":{"name":"updated_at","type":"timestamp","nullable":true,"default":null,"comment":"","isPrimaryKey":false,"isForeignKey":false,"relation":[],"autoIncrement":false}},"indexes":{"PRIMARY":{"name":"PRIMARY","columns":{"1":{"name":"id","sub_part":null}},"unique":true,"type":"BTREE","comment":"","null":null},"":{"name":null,"columns":{"":{"name":null,"sub_part":null}},"unique":true,"type":null,"comment":null,"null":"NULL"}},"foreignKeys":[]},"indikator_news_newsletter_logs":{"name":"indikator_news_newsletter_logs","engine":"InnoDB","collation":"utf8mb4_unicode_ci","comment":"","primaryKey":"id","columns":{"id":{"name":"id","type":"int(10) unsigned","nullable":false,"default":null,"comment":"","isPrimaryKey":true,"isForeignKey":false,"relation":[],"autoIncrement":true},"news_id":{"name":"news_id","type":"int(10) unsigned","nullable":true,"default":null,"comment":"","isPrimaryKey":false,"isForeignKey":false,"relation":[],"autoIncrement":false},"subscriber_id":{"name":"subscriber_id","type":"int(10) unsigned","nullable":true,"default":null,"comment":"","isPrimaryKey":false,"isForeignKey":false,"relation":[],"autoIncrement":false},"queued_at":{"name":"queued_at","type":"datetime","nullable":false,"default":null,"comment":"","isPrimaryKey":false,"isForeignKey":false,"relation":[],"autoIncrement":false},"send_at":{"name":"send_at","type":"datetime","nullable":true,"default":null,"comment":"","isPrimaryKey":false,"isForeignKey":false,"relation":[],"autoIncrement":false},"viewed_at":{"name":"viewed_at","type":"datetime","nullable":true,"default":null,"comment":"","isPrimaryKey":false,"isForeignKey":false,"relation":[],"autoIncrement":false},"clicked_at":{"name":"clicked_at","type":"datetime","nullable":true,"default":null,"comment":"","isPrimaryKey":false,"isForeignKey":false,"relation":[],"autoIncrement":false},"status":{"name":"status","type":"varchar(255)","nullable":false,"default":null,"comment":"","isPrimaryKey":false,"isForeignKey":false,"relation":[],"autoIncrement":false},"job_id":{"name":"job_id","type":"int(10) unsigned","nullable":true,"default":null,"comment":"","isPrimaryKey":false,"isForeignKey":false,"relation":[],"autoIncrement":false},"hash":{"name":"hash","type":"varchar(255)","nullable":true,"default":null,"comment":"","isPrimaryKey":false,"isForeignKey":false,"relation":[],"autoIncrement":false}},"indexes":{"PRIMARY":{"name":"PRIMARY","columns":{"1":{"name":"id","sub_part":null}},"unique":true,"type":"BTREE","comment":"","null":null},"":{"name":null,"columns":{"":{"name":null,"sub_part":null}},"unique":true,"type":null,"comment":null,"null":"NULL"}},"foreignKeys":[]},"indikator_news_posts":{"name":"indikator_news_posts","engine":"InnoDB","collation":"utf8mb4_unicode_ci","comment":"","primaryKey":"id","columns":{"id":{"name":"id","type":"int(10) unsigned","nullable":false,"default":null,"comment":"","isPrimaryKey":true,"isForeignKey":false,"relation":[],"autoIncrement":true},"title":{"name":"title","type":"varchar(100)","nullable":false,"default":null,"comment":"","isPrimaryKey":false,"isForeignKey":false,"relation":[],"autoIncrement":false},"slug":{"name":"slug","type":"varchar(100)","nullable":false,"default":null,"comment":"","isPrimaryKey":false,"isForeignKey":false,"relation":[],"autoIncrement":false},"introductory":{"name":"introductory","type":"text","nullable":true,"default":null,"comment":"","isPrimaryKey":false,"isForeignKey":false,"relation":[],"autoIncrement":false},"content":{"name":"content","type":"longtext","nullable":true,"default":null,"comment":"","isPrimaryKey":false,"isForeignKey":false,"relation":[],"autoIncrement":false},"published_at":{"name":"published_at","type":"timestamp","nullable":true,"default":null,"comment":"","isPrimaryKey":false,"isForeignKey":false,"relation":[],"autoIncrement":false},"status":{"name":"status","type":"varchar(1)","nullable":false,"default":"1","comment":"","isPrimaryKey":false,"isForeignKey":false,"relation":[],"autoIncrement":false},"statistics":{"name":"statistics","type":"int(11)","nullable":false,"default":"0","comment":"","isPrimaryKey":false,"isForeignKey":false,"relation":[],"autoIncrement":false},"created_at":{"name":"created_at","type":"timestamp","nullable":true,"default":null,"comment":"","isPrimaryKey":false,"isForeignKey":false,"relation":[],"autoIncrement":false},"updated_at":{"name":"updated_at","type":"timestamp","nullable":true,"default":null,"comment":"","isPrimaryKey":false,"isForeignKey":false,"relation":[],"autoIncrement":false},"image":{"name":"image","type":"varchar(200)","nullable":true,"default":null,"comment":"","isPrimaryKey":false,"isForeignKey":false,"relation":[],"autoIncrement":false},"featured":{"name":"featured","type":"varchar(1)","nullable":false,"default":"2","comment":"","isPrimaryKey":false,"isForeignKey":false,"relation":[],"autoIncrement":false},"last_send_at":{"name":"last_send_at","type":"datetime","nullable":true,"default":null,"comment":"","isPrimaryKey":false,"isForeignKey":false,"relation":[],"autoIncrement":false},"category_id":{"name":"category_id","type":"varchar(3)","nullable":false,"default":"0","comment":"","isPrimaryKey":false,"isForeignKey":false,"relation":[],"autoIncrement":false}},"indexes":{"PRIMARY":{"name":"PRIMARY","columns":{"1":{"name":"id","sub_part":null}},"unique":true,"type":"BTREE","comment":"","null":null},"":{"name":null,"columns":{"":{"name":null,"sub_part":null}},"unique":true,"type":null,"comment":null,"null":"NULL"}},"foreignKeys":[]},"indikator_news_relations":{"name":"indikator_news_relations","engine":"InnoDB","collation":"utf8mb4_unicode_ci","comment":"","primaryKey":["subscriber_id","categories_id"],"columns":{"subscriber_id":{"name":"subscriber_id","type":"int(10) unsigned","nullable":false,"default":null,"comment":"","isPrimaryKey":true,"isForeignKey":false,"relation":[],"autoIncrement":false},"categories_id":{"name":"categories_id","type":"int(10) unsigned","nullable":false,"default":null,"comment":"","isPrimaryKey":true,"isForeignKey":false,"relation":[],"autoIncrement":false}},"indexes":{"PRIMARY":{"name":"PRIMARY","columns":{"1":{"name":"subscriber_id","sub_part":null},"2":{"name":"categories_id","sub_part":null}},"unique":true,"type":"BTREE","comment":"","null":null},"":{"name":null,"columns":{"":{"name":null,"sub_part":null}},"unique":true,"type":null,"comment":null,"null":"NULL"}},"foreignKeys":[]},"indikator_news_subscribers":{"name":"indikator_news_subscribers","engine":"InnoDB","collation":"utf8mb4_unicode_ci","comment":"","primaryKey":"id","columns":{"id":{"name":"id","type":"int(10) unsigned","nullable":false,"default":null,"comment":"","isPrimaryKey":true,"isForeignKey":false,"relation":[],"autoIncrement":true},"name":{"name":"name","type":"varchar(100)","nullable":false,"default":null,"comment":"","isPrimaryKey":false,"isForeignKey":false,"relation":[],"autoIncrement":false},"email":{"name":"email","type":"varchar(100)","nullable":false,"default":null,"comment":"","isPrimaryKey":false,"isForeignKey":false,"relation":[],"autoIncrement":false},"common":{"name":"common","type":"text","nullable":true,"default":null,"comment":"","isPrimaryKey":false,"isForeignKey":false,"relation":[],"autoIncrement":false},"created":{"name":"created","type":"varchar(1)","nullable":false,"default":"1","comment":"","isPrimaryKey":false,"isForeignKey":false,"relation":[],"autoIncrement":false},"statistics":{"name":"statistics","type":"int(11)","nullable":false,"default":"0","comment":"","isPrimaryKey":false,"isForeignKey":false,"relation":[],"autoIncrement":false},"created_at":{"name":"created_at","type":"timestamp","nullable":true,"default":null,"comment":"","isPrimaryKey":false,"isForeignKey":false,"relation":[],"autoIncrement":false},"updated_at":{"name":"updated_at","type":"timestamp","nullable":true,"default":null,"comment":"","isPrimaryKey":false,"isForeignKey":false,"relation":[],"autoIncrement":false},"status":{"name":"status","type":"varchar(1)","nullable":false,"default":"1","comment":"","isPrimaryKey":false,"isForeignKey":false,"relation":[],"autoIncrement":false},"locale":{"name":"locale","type":"varchar(5)","nullable":true,"default":null,"comment":"","isPrimaryKey":false,"isForeignKey":false,"relation":[],"autoIncrement":false}},"indexes":{"PRIMARY":{"name":"PRIMARY","columns":{"1":{"name":"id","sub_part":null}},"unique":true,"type":"BTREE","comment":"","null":null},"":{"name":null,"columns":{"":{"name":null,"sub_part":null}},"unique":true,"type":null,"comment":null,"null":"NULL"}},"foreignKeys":[]},"jobs":{"name":"jobs","engine":"InnoDB","collation":"utf8mb4_unicode_ci","comment":"","primaryKey":"id","columns":{"id":{"name":"id","type":"bigint(20) unsigned","nullable":false,"default":null,"comment":"","isPrimaryKey":true,"isForeignKey":false,"relation":[],"autoIncrement":true},"queue":{"name":"queue","type":"varchar(191)","nullable":false,"default":null,"comment":"","isPrimaryKey":false,"isForeignKey":false,"relation":[],"autoIncrement":false},"payload":{"name":"payload","type":"text","nullable":false,"default":null,"comment":"","isPrimaryKey":false,"isForeignKey":false,"relation":[],"autoIncrement":false},"attempts":{"name":"attempts","type":"tinyint(3) unsigned","nullable":false,"default":null,"comment":"","isPrimaryKey":false,"isForeignKey":false,"relation":[],"autoIncrement":false},"reserved_at":{"name":"reserved_at","type":"int(10) unsigned","nullable":true,"default":null,"comment":"","isPrimaryKey":false,"isForeignKey":false,"relation":[],"autoIncrement":false},"available_at":{"name":"available_at","type":"int(10) unsigned","nullable":false,"default":null,"comment":"","isPrimaryKey":false,"isForeignKey":false,"relation":[],"autoIncrement":false},"created_at":{"name":"created_at","type":"int(10) unsigned","nullable":false,"default":null,"comment":"","isPrimaryKey":false,"isForeignKey":false,"relation":[],"autoIncrement":false}},"indexes":{"PRIMARY":{"name":"PRIMARY","columns":{"1":{"name":"id","sub_part":null}},"unique":true,"type":"BTREE","comment":"","null":null},"jobs_queue_reserved_at_index":{"name":"jobs_queue_reserved_at_index","columns":{"1":{"name":"queue","sub_part":null},"2":{"name":"reserved_at","sub_part":null}},"unique":false,"type":"BTREE","comment":"","null":null},"":{"name":null,"columns":{"":{"name":null,"sub_part":null}},"unique":true,"type":null,"comment":null,"null":"NULL"}},"foreignKeys":[]},"migrations":{"name":"migrations","engine":"InnoDB","collation":"utf8mb4_unicode_ci","comment":"","primaryKey":"id","columns":{"id":{"name":"id","type":"int(10) unsigned","nullable":false,"default":null,"comment":"","isPrimaryKey":true,"isForeignKey":false,"relation":[],"autoIncrement":true},"migration":{"name":"migration","type":"varchar(191)","nullable":false,"default":null,"comment":"","isPrimaryKey":false,"isForeignKey":false,"relation":[],"autoIncrement":false},"batch":{"name":"batch","type":"int(11)","nullable":false,"default":null,"comment":"","isPrimaryKey":false,"isForeignKey":false,"relation":[],"autoIncrement":false}},"indexes":{"PRIMARY":{"name":"PRIMARY","columns":{"1":{"name":"id","sub_part":null}},"unique":true,"type":"BTREE","comment":"","null":null},"":{"name":null,"columns":{"":{"name":null,"sub_part":null}},"unique":true,"type":null,"comment":null,"null":"NULL"}},"foreignKeys":[]},"rainlab_blog_categories":{"name":"rainlab_blog_categories","engine":"InnoDB","collation":"utf8mb4_unicode_ci","comment":"","primaryKey":"id","columns":{"id":{"name":"id","type":"int(10) unsigned","nullable":false,"default":null,"comment":"","isPrimaryKey":true,"isForeignKey":false,"relation":[],"autoIncrement":true},"name":{"name":"name","type":"varchar(191)","nullable":true,"default":null,"comment":"","isPrimaryKey":false,"isForeignKey":false,"relation":[],"autoIncrement":false},"slug":{"name":"slug","type":"varchar(191)","nullable":true,"default":null,"comment":"","isPrimaryKey":false,"isForeignKey":false,"relation":[],"autoIncrement":false},"code":{"name":"code","type":"varchar(191)","nullable":true,"default":null,"comment":"","isPrimaryKey":false,"isForeignKey":false,"relation":[],"autoIncrement":false},"description":{"name":"description","type":"text","nullable":true,"default":null,"comment":"","isPrimaryKey":false,"isForeignKey":false,"relation":[],"autoIncrement":false},"parent_id":{"name":"parent_id","type":"int(10) unsigned","nullable":true,"default":null,"comment":"","isPrimaryKey":false,"isForeignKey":false,"relation":[],"autoIncrement":false},"nest_left":{"name":"nest_left","type":"int(11)","nullable":true,"default":null,"comment":"","isPrimaryKey":false,"isForeignKey":false,"relation":[],"autoIncrement":false},"nest_right":{"name":"nest_right","type":"int(11)","nullable":true,"default":null,"comment":"","isPrimaryKey":false,"isForeignKey":false,"relation":[],"autoIncrement":false},"nest_depth":{"name":"nest_depth","type":"int(11)","nullable":true,"default":null,"comment":"","isPrimaryKey":false,"isForeignKey":false,"relation":[],"autoIncrement":false},"created_at":{"name":"created_at","type":"timestamp","nullable":true,"default":null,"comment":"","isPrimaryKey":false,"isForeignKey":false,"relation":[],"autoIncrement":false},"updated_at":{"name":"updated_at","type":"timestamp","nullable":true,"default":null,"comment":"","isPrimaryKey":false,"isForeignKey":false,"relation":[],"autoIncrement":false}},"indexes":{"PRIMARY":{"name":"PRIMARY","columns":{"1":{"name":"id","sub_part":null}},"unique":true,"type":"BTREE","comment":"","null":null},"rainlab_blog_categories_slug_index":{"name":"rainlab_blog_categories_slug_index","columns":{"1":{"name":"slug","sub_part":null}},"unique":false,"type":"BTREE","comment":"","null":null},"rainlab_blog_categories_parent_id_index":{"name":"rainlab_blog_categories_parent_id_index","columns":{"1":{"name":"parent_id","sub_part":null}},"unique":false,"type":"BTREE","comment":"","null":null},"":{"name":null,"columns":{"":{"name":null,"sub_part":null}},"unique":true,"type":null,"comment":null,"null":"NULL"}},"foreignKeys":[]},"rainlab_blog_posts":{"name":"rainlab_blog_posts","engine":"InnoDB","collation":"utf8mb4_unicode_ci","comment":"","primaryKey":"id","columns":{"id":{"name":"id","type":"int(10) unsigned","nullable":false,"default":null,"comment":"","isPrimaryKey":true,"isForeignKey":false,"relation":[],"autoIncrement":true},"user_id":{"name":"user_id","type":"int(10) unsigned","nullable":true,"default":null,"comment":"","isPrimaryKey":false,"isForeignKey":false,"relation":[],"autoIncrement":false},"title":{"name":"title","type":"varchar(191)","nullable":true,"default":null,"comment":"","isPrimaryKey":false,"isForeignKey":false,"relation":[],"autoIncrement":false},"slug":{"name":"slug","type":"varchar(191)","nullable":false,"default":null,"comment":"","isPrimaryKey":false,"isForeignKey":false,"relation":[],"autoIncrement":false},"excerpt":{"name":"excerpt","type":"text","nullable":true,"default":null,"comment":"","isPrimaryKey":false,"isForeignKey":false,"relation":[],"autoIncrement":false},"content":{"name":"content","type":"longtext","nullable":true,"default":null,"comment":"","isPrimaryKey":false,"isForeignKey":false,"relation":[],"autoIncrement":false},"content_html":{"name":"content_html","type":"longtext","nullable":true,"default":null,"comment":"","isPrimaryKey":false,"isForeignKey":false,"relation":[],"autoIncrement":false},"published_at":{"name":"published_at","type":"timestamp","nullable":true,"default":null,"comment":"","isPrimaryKey":false,"isForeignKey":false,"relation":[],"autoIncrement":false},"published":{"name":"published","type":"tinyint(1)","nullable":false,"default":"0","comment":"","isPrimaryKey":false,"isForeignKey":false,"relation":[],"autoIncrement":false},"created_at":{"name":"created_at","type":"timestamp","nullable":true,"default":null,"comment":"","isPrimaryKey":false,"isForeignKey":false,"relation":[],"autoIncrement":false},"updated_at":{"name":"updated_at","type":"timestamp","nullable":true,"default":null,"comment":"","isPrimaryKey":false,"isForeignKey":false,"relation":[],"autoIncrement":false}},"indexes":{"PRIMARY":{"name":"PRIMARY","columns":{"1":{"name":"id","sub_part":null}},"unique":true,"type":"BTREE","comment":"","null":null},"rainlab_blog_posts_user_id_index":{"name":"rainlab_blog_posts_user_id_index","columns":{"1":{"name":"user_id","sub_part":null}},"unique":false,"type":"BTREE","comment":"","null":null},"rainlab_blog_posts_slug_index":{"name":"rainlab_blog_posts_slug_index","columns":{"1":{"name":"slug","sub_part":null}},"unique":false,"type":"BTREE","comment":"","null":null},"":{"name":null,"columns":{"":{"name":null,"sub_part":null}},"unique":true,"type":null,"comment":null,"null":"NULL"}},"foreignKeys":[]},"rainlab_blog_posts_categories":{"name":"rainlab_blog_posts_categories","engine":"InnoDB","collation":"utf8mb4_unicode_ci","comment":"","primaryKey":["post_id","category_id"],"columns":{"post_id":{"name":"post_id","type":"int(10) unsigned","nullable":false,"default":null,"comment":"","isPrimaryKey":true,"isForeignKey":false,"relation":[],"autoIncrement":false},"category_id":{"name":"category_id","type":"int(10) unsigned","nullable":false,"default":null,"comment":"","isPrimaryKey":true,"isForeignKey":false,"relation":[],"autoIncrement":false}},"indexes":{"PRIMARY":{"name":"PRIMARY","columns":{"1":{"name":"post_id","sub_part":null},"2":{"name":"category_id","sub_part":null}},"unique":true,"type":"BTREE","comment":"","null":null},"":{"name":null,"columns":{"":{"name":null,"sub_part":null}},"unique":true,"type":null,"comment":null,"null":"NULL"}},"foreignKeys":[]},"sessions":{"name":"sessions","engine":"InnoDB","collation":"utf8mb4_unicode_ci","comment":"","primaryKey":"id","columns":{"id":{"name":"id","type":"varchar(191)","nullable":false,"default":null,"comment":"","isPrimaryKey":true,"isForeignKey":false,"relation":[],"autoIncrement":false},"payload":{"name":"payload","type":"text","nullable":true,"default":null,"comment":"","isPrimaryKey":false,"isForeignKey":false,"relation":[],"autoIncrement":false},"last_activity":{"name":"last_activity","type":"int(11)","nullable":true,"default":null,"comment":"","isPrimaryKey":false,"isForeignKey":false,"relation":[],"autoIncrement":false},"user_id":{"name":"user_id","type":"int(10) unsigned","nullable":true,"default":null,"comment":"","isPrimaryKey":false,"isForeignKey":false,"relation":[],"autoIncrement":false},"ip_address":{"name":"ip_address","type":"varchar(45)","nullable":true,"default":null,"comment":"","isPrimaryKey":false,"isForeignKey":false,"relation":[],"autoIncrement":false},"user_agent":{"name":"user_agent","type":"text","nullable":true,"default":null,"comment":"","isPrimaryKey":false,"isForeignKey":false,"relation":[],"autoIncrement":false}},"indexes":{"sessions_id_unique":{"name":"sessions_id_unique","columns":{"1":{"name":"id","sub_part":null}},"unique":true,"type":"BTREE","comment":"","null":null},"":{"name":null,"columns":{"":{"name":null,"sub_part":null}},"unique":true,"type":null,"comment":null,"null":"NULL"}},"foreignKeys":[]},"system_event_logs":{"name":"system_event_logs","engine":"InnoDB","collation":"utf8mb4_unicode_ci","comment":"","primaryKey":"id","columns":{"id":{"name":"id","type":"int(10) unsigned","nullable":false,"default":null,"comment":"","isPrimaryKey":true,"isForeignKey":false,"relation":[],"autoIncrement":true},"level":{"name":"level","type":"varchar(191)","nullable":true,"default":null,"comment":"","isPrimaryKey":false,"isForeignKey":false,"relation":[],"autoIncrement":false},"message":{"name":"message","type":"text","nullable":true,"default":null,"comment":"","isPrimaryKey":false,"isForeignKey":false,"relation":[],"autoIncrement":false},"details":{"name":"details","type":"mediumtext","nullable":true,"default":null,"comment":"","isPrimaryKey":false,"isForeignKey":false,"relation":[],"autoIncrement":false},"created_at":{"name":"created_at","type":"timestamp","nullable":true,"default":null,"comment":"","isPrimaryKey":false,"isForeignKey":false,"relation":[],"autoIncrement":false},"updated_at":{"name":"updated_at","type":"timestamp","nullable":true,"default":null,"comment":"","isPrimaryKey":false,"isForeignKey":false,"relation":[],"autoIncrement":false}},"indexes":{"PRIMARY":{"name":"PRIMARY","columns":{"1":{"name":"id","sub_part":null}},"unique":true,"type":"BTREE","comment":"","null":null},"system_event_logs_level_index":{"name":"system_event_logs_level_index","columns":{"1":{"name":"level","sub_part":null}},"unique":false,"type":"BTREE","comment":"","null":null},"":{"name":null,"columns":{"":{"name":null,"sub_part":null}},"unique":true,"type":null,"comment":null,"null":"NULL"}},"foreignKeys":[]},"system_files":{"name":"system_files","engine":"InnoDB","collation":"utf8mb4_unicode_ci","comment":"","primaryKey":"id","columns":{"id":{"name":"id","type":"int(10) unsigned","nullable":false,"default":null,"comment":"","isPrimaryKey":true,"isForeignKey":false,"relation":[],"autoIncrement":true},"disk_name":{"name":"disk_name","type":"varchar(191)","nullable":false,"default":null,"comment":"","isPrimaryKey":false,"isForeignKey":false,"relation":[],"autoIncrement":false},"file_name":{"name":"file_name","type":"varchar(191)","nullable":false,"default":null,"comment":"","isPrimaryKey":false,"isForeignKey":false,"relation":[],"autoIncrement":false},"file_size":{"name":"file_size","type":"int(11)","nullable":false,"default":null,"comment":"","isPrimaryKey":false,"isForeignKey":false,"relation":[],"autoIncrement":false},"content_type":{"name":"content_type","type":"varchar(191)","nullable":false,"default":null,"comment":"","isPrimaryKey":false,"isForeignKey":false,"relation":[],"autoIncrement":false},"title":{"name":"title","type":"varchar(191)","nullable":true,"default":null,"comment":"","isPrimaryKey":false,"isForeignKey":false,"relation":[],"autoIncrement":false},"description":{"name":"description","type":"text","nullable":true,"default":null,"comment":"","isPrimaryKey":false,"isForeignKey":false,"relation":[],"autoIncrement":false},"field":{"name":"field","type":"varchar(191)","nullable":true,"default":null,"comment":"","isPrimaryKey":false,"isForeignKey":false,"relation":[],"autoIncrement":false},"attachment_id":{"name":"attachment_id","type":"varchar(191)","nullable":true,"default":null,"comment":"","isPrimaryKey":false,"isForeignKey":false,"relation":[],"autoIncrement":false},"attachment_type":{"name":"attachment_type","type":"varchar(191)","nullable":true,"default":null,"comment":"","isPrimaryKey":false,"isForeignKey":false,"relation":[],"autoIncrement":false},"is_public":{"name":"is_public","type":"tinyint(1)","nullable":false,"default":"1","comment":"","isPrimaryKey":false,"isForeignKey":false,"relation":[],"autoIncrement":false},"sort_order":{"name":"sort_order","type":"int(11)","nullable":true,"default":null,"comment":"","isPrimaryKey":false,"isForeignKey":false,"relation":[],"autoIncrement":false},"created_at":{"name":"created_at","type":"timestamp","nullable":true,"default":null,"comment":"","isPrimaryKey":false,"isForeignKey":false,"relation":[],"autoIncrement":false},"updated_at":{"name":"updated_at","type":"timestamp","nullable":true,"default":null,"comment":"","isPrimaryKey":false,"isForeignKey":false,"relation":[],"autoIncrement":false}},"indexes":{"PRIMARY":{"name":"PRIMARY","columns":{"1":{"name":"id","sub_part":null}},"unique":true,"type":"BTREE","comment":"","null":null},"system_files_field_index":{"name":"system_files_field_index","columns":{"1":{"name":"field","sub_part":null}},"unique":false,"type":"BTREE","comment":"","null":null},"system_files_attachment_id_index":{"name":"system_files_attachment_id_index","columns":{"1":{"name":"attachment_id","sub_part":null}},"unique":false,"type":"BTREE","comment":"","null":null},"system_files_attachment_type_index":{"name":"system_files_attachment_type_index","columns":{"1":{"name":"attachment_type","sub_part":null}},"unique":false,"type":"BTREE","comment":"","null":null},"":{"name":null,"columns":{"":{"name":null,"sub_part":null}},"unique":true,"type":null,"comment":null,"null":"NULL"}},"foreignKeys":[]},"system_mail_layouts":{"name":"system_mail_layouts","engine":"InnoDB","collation":"utf8mb4_unicode_ci","comment":"","primaryKey":"id","columns":{"id":{"name":"id","type":"int(10) unsigned","nullable":false,"default":null,"comment":"","isPrimaryKey":true,"isForeignKey":false,"relation":[],"autoIncrement":true},"name":{"name":"name","type":"varchar(191)","nullable":true,"default":null,"comment":"","isPrimaryKey":false,"isForeignKey":false,"relation":[],"autoIncrement":false},"code":{"name":"code","type":"varchar(191)","nullable":true,"default":null,"comment":"","isPrimaryKey":false,"isForeignKey":false,"relation":[],"autoIncrement":false},"content_html":{"name":"content_html","type":"text","nullable":true,"default":null,"comment":"","isPrimaryKey":false,"isForeignKey":false,"relation":[],"autoIncrement":false},"content_text":{"name":"content_text","type":"text","nullable":true,"default":null,"comment":"","isPrimaryKey":false,"isForeignKey":false,"relation":[],"autoIncrement":false},"content_css":{"name":"content_css","type":"text","nullable":true,"default":null,"comment":"","isPrimaryKey":false,"isForeignKey":false,"relation":[],"autoIncrement":false},"is_locked":{"name":"is_locked","type":"tinyint(1)","nullable":false,"default":"0","comment":"","isPrimaryKey":false,"isForeignKey":false,"relation":[],"autoIncrement":false},"created_at":{"name":"created_at","type":"timestamp","nullable":true,"default":null,"comment":"","isPrimaryKey":false,"isForeignKey":false,"relation":[],"autoIncrement":false},"updated_at":{"name":"updated_at","type":"timestamp","nullable":true,"default":null,"comment":"","isPrimaryKey":false,"isForeignKey":false,"relation":[],"autoIncrement":false}},"indexes":{"PRIMARY":{"name":"PRIMARY","columns":{"1":{"name":"id","sub_part":null}},"unique":true,"type":"BTREE","comment":"","null":null},"":{"name":null,"columns":{"":{"name":null,"sub_part":null}},"unique":true,"type":null,"comment":null,"null":"NULL"}},"foreignKeys":[]},"system_mail_partials":{"name":"system_mail_partials","engine":"InnoDB","collation":"utf8mb4_unicode_ci","comment":"","primaryKey":"id","columns":{"id":{"name":"id","type":"int(10) unsigned","nullable":false,"default":null,"comment":"","isPrimaryKey":true,"isForeignKey":false,"relation":[],"autoIncrement":true},"name":{"name":"name","type":"varchar(191)","nullable":true,"default":null,"comment":"","isPrimaryKey":false,"isForeignKey":false,"relation":[],"autoIncrement":false},"code":{"name":"code","type":"varchar(191)","nullable":true,"default":null,"comment":"","isPrimaryKey":false,"isForeignKey":false,"relation":[],"autoIncrement":false},"content_html":{"name":"content_html","type":"text","nullable":true,"default":null,"comment":"","isPrimaryKey":false,"isForeignKey":false,"relation":[],"autoIncrement":false},"content_text":{"name":"content_text","type":"text","nullable":true,"default":null,"comment":"","isPrimaryKey":false,"isForeignKey":false,"relation":[],"autoIncrement":false},"is_custom":{"name":"is_custom","type":"tinyint(1)","nullable":false,"default":"0","comment":"","isPrimaryKey":false,"isForeignKey":false,"relation":[],"autoIncrement":false},"created_at":{"name":"created_at","type":"timestamp","nullable":true,"default":null,"comment":"","isPrimaryKey":false,"isForeignKey":false,"relation":[],"autoIncrement":false},"updated_at":{"name":"updated_at","type":"timestamp","nullable":true,"default":null,"comment":"","isPrimaryKey":false,"isForeignKey":false,"relation":[],"autoIncrement":false}},"indexes":{"PRIMARY":{"name":"PRIMARY","columns":{"1":{"name":"id","sub_part":null}},"unique":true,"type":"BTREE","comment":"","null":null},"":{"name":null,"columns":{"":{"name":null,"sub_part":null}},"unique":true,"type":null,"comment":null,"null":"NULL"}},"foreignKeys":[]},"system_mail_templates":{"name":"system_mail_templates","engine":"InnoDB","collation":"utf8mb4_unicode_ci","comment":"","primaryKey":"id","columns":{"id":{"name":"id","type":"int(10) unsigned","nullable":false,"default":null,"comment":"","isPrimaryKey":true,"isForeignKey":false,"relation":[],"autoIncrement":true},"code":{"name":"code","type":"varchar(191)","nullable":true,"default":null,"comment":"","isPrimaryKey":false,"isForeignKey":false,"relation":[],"autoIncrement":false},"subject":{"name":"subject","type":"varchar(191)","nullable":true,"default":null,"comment":"","isPrimaryKey":false,"isForeignKey":false,"relation":[],"autoIncrement":false},"description":{"name":"description","type":"text","nullable":true,"default":null,"comment":"","isPrimaryKey":false,"isForeignKey":false,"relation":[],"autoIncrement":false},"content_html":{"name":"content_html","type":"text","nullable":true,"default":null,"comment":"","isPrimaryKey":false,"isForeignKey":false,"relation":[],"autoIncrement":false},"content_text":{"name":"content_text","type":"text","nullable":true,"default":null,"comment":"","isPrimaryKey":false,"isForeignKey":false,"relation":[],"autoIncrement":false},"layout_id":{"name":"layout_id","type":"int(11)","nullable":true,"default":null,"comment":"","isPrimaryKey":false,"isForeignKey":false,"relation":[],"autoIncrement":false},"is_custom":{"name":"is_custom","type":"tinyint(1)","nullable":false,"default":"0","comment":"","isPrimaryKey":false,"isForeignKey":false,"relation":[],"autoIncrement":false},"created_at":{"name":"created_at","type":"timestamp","nullable":true,"default":null,"comment":"","isPrimaryKey":false,"isForeignKey":false,"relation":[],"autoIncrement":false},"updated_at":{"name":"updated_at","type":"timestamp","nullable":true,"default":null,"comment":"","isPrimaryKey":false,"isForeignKey":false,"relation":[],"autoIncrement":false}},"indexes":{"PRIMARY":{"name":"PRIMARY","columns":{"1":{"name":"id","sub_part":null}},"unique":true,"type":"BTREE","comment":"","null":null},"system_mail_templates_layout_id_index":{"name":"system_mail_templates_layout_id_index","columns":{"1":{"name":"layout_id","sub_part":null}},"unique":false,"type":"BTREE","comment":"","null":null},"":{"name":null,"columns":{"":{"name":null,"sub_part":null}},"unique":true,"type":null,"comment":null,"null":"NULL"}},"foreignKeys":[]},"system_parameters":{"name":"system_parameters","engine":"InnoDB","collation":"utf8mb4_unicode_ci","comment":"","primaryKey":"id","columns":{"id":{"name":"id","type":"int(10) unsigned","nullable":false,"default":null,"comment":"","isPrimaryKey":true,"isForeignKey":false,"relation":[],"autoIncrement":true},"namespace":{"name":"namespace","type":"varchar(100)","nullable":false,"default":null,"comment":"","isPrimaryKey":false,"isForeignKey":false,"relation":[],"autoIncrement":false},"group":{"name":"group","type":"varchar(50)","nullable":false,"default":null,"comment":"","isPrimaryKey":false,"isForeignKey":false,"relation":[],"autoIncrement":false},"item":{"name":"item","type":"varchar(150)","nullable":false,"default":null,"comment":"","isPrimaryKey":false,"isForeignKey":false,"relation":[],"autoIncrement":false},"value":{"name":"value","type":"text","nullable":true,"default":null,"comment":"","isPrimaryKey":false,"isForeignKey":false,"relation":[],"autoIncrement":false}},"indexes":{"PRIMARY":{"name":"PRIMARY","columns":{"1":{"name":"id","sub_part":null}},"unique":true,"type":"BTREE","comment":"","null":null},"item_index":{"name":"item_index","columns":{"1":{"name":"namespace","sub_part":null},"2":{"name":"group","sub_part":null},"3":{"name":"item","sub_part":null}},"unique":false,"type":"BTREE","comment":"","null":null},"":{"name":null,"columns":{"":{"name":null,"sub_part":null}},"unique":true,"type":null,"comment":null,"null":"NULL"}},"foreignKeys":[]},"system_plugin_history":{"name":"system_plugin_history","engine":"InnoDB","collation":"utf8mb4_unicode_ci","comment":"","primaryKey":"id","columns":{"id":{"name":"id","type":"int(10) unsigned","nullable":false,"default":null,"comment":"","isPrimaryKey":true,"isForeignKey":false,"relation":[],"autoIncrement":true},"code":{"name":"code","type":"varchar(191)","nullable":false,"default":null,"comment":"","isPrimaryKey":false,"isForeignKey":false,"relation":[],"autoIncrement":false},"type":{"name":"type","type":"varchar(20)","nullable":false,"default":null,"comment":"","isPrimaryKey":false,"isForeignKey":false,"relation":[],"autoIncrement":false},"version":{"name":"version","type":"varchar(50)","nullable":false,"default":null,"comment":"","isPrimaryKey":false,"isForeignKey":false,"relation":[],"autoIncrement":false},"detail":{"name":"detail","type":"text","nullable":true,"default":null,"comment":"","isPrimaryKey":false,"isForeignKey":false,"relation":[],"autoIncrement":false},"created_at":{"name":"created_at","type":"timestamp","nullable":true,"default":null,"comment":"","isPrimaryKey":false,"isForeignKey":false,"relation":[],"autoIncrement":false}},"indexes":{"PRIMARY":{"name":"PRIMARY","columns":{"1":{"name":"id","sub_part":null}},"unique":true,"type":"BTREE","comment":"","null":null},"system_plugin_history_code_index":{"name":"system_plugin_history_code_index","columns":{"1":{"name":"code","sub_part":null}},"unique":false,"type":"BTREE","comment":"","null":null},"system_plugin_history_type_index":{"name":"system_plugin_history_type_index","columns":{"1":{"name":"type","sub_part":null}},"unique":false,"type":"BTREE","comment":"","null":null},"":{"name":null,"columns":{"":{"name":null,"sub_part":null}},"unique":true,"type":null,"comment":null,"null":"NULL"}},"foreignKeys":[]},"system_plugin_versions":{"name":"system_plugin_versions","engine":"InnoDB","collation":"utf8mb4_unicode_ci","comment":"","primaryKey":"id","columns":{"id":{"name":"id","type":"int(10) unsigned","nullable":false,"default":null,"comment":"","isPrimaryKey":true,"isForeignKey":false,"relation":[],"autoIncrement":true},"code":{"name":"code","type":"varchar(191)","nullable":false,"default":null,"comment":"","isPrimaryKey":false,"isForeignKey":false,"relation":[],"autoIncrement":false},"version":{"name":"version","type":"varchar(50)","nullable":false,"default":null,"comment":"","isPrimaryKey":false,"isForeignKey":false,"relation":[],"autoIncrement":false},"created_at":{"name":"created_at","type":"timestamp","nullable":true,"default":null,"comment":"","isPrimaryKey":false,"isForeignKey":false,"relation":[],"autoIncrement":false},"is_disabled":{"name":"is_disabled","type":"tinyint(1)","nullable":false,"default":"0","comment":"","isPrimaryKey":false,"isForeignKey":false,"relation":[],"autoIncrement":false},"is_frozen":{"name":"is_frozen","type":"tinyint(1)","nullable":false,"default":"0","comment":"","isPrimaryKey":false,"isForeignKey":false,"relation":[],"autoIncrement":false}},"indexes":{"PRIMARY":{"name":"PRIMARY","columns":{"1":{"name":"id","sub_part":null}},"unique":true,"type":"BTREE","comment":"","null":null},"system_plugin_versions_code_index":{"name":"system_plugin_versions_code_index","columns":{"1":{"name":"code","sub_part":null}},"unique":false,"type":"BTREE","comment":"","null":null},"":{"name":null,"columns":{"":{"name":null,"sub_part":null}},"unique":true,"type":null,"comment":null,"null":"NULL"}},"foreignKeys":[]},"system_request_logs":{"name":"system_request_logs","engine":"InnoDB","collation":"utf8mb4_unicode_ci","comment":"","primaryKey":"id","columns":{"id":{"name":"id","type":"int(10) unsigned","nullable":false,"default":null,"comment":"","isPrimaryKey":true,"isForeignKey":false,"relation":[],"autoIncrement":true},"status_code":{"name":"status_code","type":"int(11)","nullable":true,"default":null,"comment":"","isPrimaryKey":false,"isForeignKey":false,"relation":[],"autoIncrement":false},"url":{"name":"url","type":"varchar(191)","nullable":true,"default":null,"comment":"","isPrimaryKey":false,"isForeignKey":false,"relation":[],"autoIncrement":false},"referer":{"name":"referer","type":"text","nullable":true,"default":null,"comment":"","isPrimaryKey":false,"isForeignKey":false,"relation":[],"autoIncrement":false},"count":{"name":"count","type":"int(11)","nullable":false,"default":"0","comment":"","isPrimaryKey":false,"isForeignKey":false,"relation":[],"autoIncrement":false},"created_at":{"name":"created_at","type":"timestamp","nullable":true,"default":null,"comment":"","isPrimaryKey":false,"isForeignKey":false,"relation":[],"autoIncrement":false},"updated_at":{"name":"updated_at","type":"timestamp","nullable":true,"default":null,"comment":"","isPrimaryKey":false,"isForeignKey":false,"relation":[],"autoIncrement":false}},"indexes":{"PRIMARY":{"name":"PRIMARY","columns":{"1":{"name":"id","sub_part":null}},"unique":true,"type":"BTREE","comment":"","null":null},"":{"name":null,"columns":{"":{"name":null,"sub_part":null}},"unique":true,"type":null,"comment":null,"null":"NULL"}},"foreignKeys":[]},"system_revisions":{"name":"system_revisions","engine":"InnoDB","collation":"utf8mb4_unicode_ci","comment":"","primaryKey":"id","columns":{"id":{"name":"id","type":"int(10) unsigned","nullable":false,"default":null,"comment":"","isPrimaryKey":true,"isForeignKey":false,"relation":[],"autoIncrement":true},"user_id":{"name":"user_id","type":"int(10) unsigned","nullable":true,"default":null,"comment":"","isPrimaryKey":false,"isForeignKey":false,"relation":[],"autoIncrement":false},"field":{"name":"field","type":"varchar(191)","nullable":true,"default":null,"comment":"","isPrimaryKey":false,"isForeignKey":false,"relation":[],"autoIncrement":false},"cast":{"name":"cast","type":"varchar(191)","nullable":true,"default":null,"comment":"","isPrimaryKey":false,"isForeignKey":false,"relation":[],"autoIncrement":false},"old_value":{"name":"old_value","type":"text","nullable":true,"default":null,"comment":"","isPrimaryKey":false,"isForeignKey":false,"relation":[],"autoIncrement":false},"new_value":{"name":"new_value","type":"text","nullable":true,"default":null,"comment":"","isPrimaryKey":false,"isForeignKey":false,"relation":[],"autoIncrement":false},"revisionable_type":{"name":"revisionable_type","type":"varchar(191)","nullable":false,"default":null,"comment":"","isPrimaryKey":false,"isForeignKey":false,"relation":[],"autoIncrement":false},"revisionable_id":{"name":"revisionable_id","type":"int(11)","nullable":false,"default":null,"comment":"","isPrimaryKey":false,"isForeignKey":false,"relation":[],"autoIncrement":false},"created_at":{"name":"created_at","type":"timestamp","nullable":true,"default":null,"comment":"","isPrimaryKey":false,"isForeignKey":false,"relation":[],"autoIncrement":false},"updated_at":{"name":"updated_at","type":"timestamp","nullable":true,"default":null,"comment":"","isPrimaryKey":false,"isForeignKey":false,"relation":[],"autoIncrement":false}},"indexes":{"PRIMARY":{"name":"PRIMARY","columns":{"1":{"name":"id","sub_part":null}},"unique":true,"type":"BTREE","comment":"","null":null},"system_revisions_revisionable_id_revisionable_type_index":{"name":"system_revisions_revisionable_id_revisionable_type_index","columns":{"1":{"name":"revisionable_id","sub_part":null},"2":{"name":"revisionable_type","sub_part":null}},"unique":false,"type":"BTREE","comment":"","null":null},"system_revisions_user_id_index":{"name":"system_revisions_user_id_index","columns":{"1":{"name":"user_id","sub_part":null}},"unique":false,"type":"BTREE","comment":"","null":null},"system_revisions_field_index":{"name":"system_revisions_field_index","columns":{"1":{"name":"field","sub_part":null}},"unique":false,"type":"BTREE","comment":"","null":null},"":{"name":null,"columns":{"":{"name":null,"sub_part":null}},"unique":true,"type":null,"comment":null,"null":"NULL"}},"foreignKeys":[]},"system_settings":{"name":"system_settings","engine":"InnoDB","collation":"utf8mb4_unicode_ci","comment":"","primaryKey":"id","columns":{"id":{"name":"id","type":"int(10) unsigned","nullable":false,"default":null,"comment":"","isPrimaryKey":true,"isForeignKey":false,"relation":[],"autoIncrement":true},"item":{"name":"item","type":"varchar(191)","nullable":true,"default":null,"comment":"","isPrimaryKey":false,"isForeignKey":false,"relation":[],"autoIncrement":false},"value":{"name":"value","type":"mediumtext","nullable":true,"default":null,"comment":"","isPrimaryKey":false,"isForeignKey":false,"relation":[],"autoIncrement":false}},"indexes":{"PRIMARY":{"name":"PRIMARY","columns":{"1":{"name":"id","sub_part":null}},"unique":true,"type":"BTREE","comment":"","null":null},"system_settings_item_index":{"name":"system_settings_item_index","columns":{"1":{"name":"item","sub_part":null}},"unique":false,"type":"BTREE","comment":"","null":null},"":{"name":null,"columns":{"":{"name":null,"sub_part":null}},"unique":true,"type":null,"comment":null,"null":"NULL"}},"foreignKeys":[]}}